compression_safeguards/__init__.py
compression_safeguards/api.py
compression_safeguards/py.typed
compression_safeguards/safeguards/__init__.py
compression_safeguards/safeguards/abc.py
compression_safeguards/safeguards/eb.py
compression_safeguards/safeguards/qois.py
compression_safeguards/safeguards/_qois/__init__.py
compression_safeguards/safeguards/_qois/__main__.py
compression_safeguards/safeguards/_qois/bound.py
compression_safeguards/safeguards/_qois/interval.py
compression_safeguards/safeguards/_qois/lexer.py
compression_safeguards/safeguards/_qois/parser.py
compression_safeguards/safeguards/_qois/typing.py
compression_safeguards/safeguards/_qois/expr/__init__.py
compression_safeguards/safeguards/_qois/expr/abc.py
compression_safeguards/safeguards/_qois/expr/abs.py
compression_safeguards/safeguards/_qois/expr/addsub.py
compression_safeguards/safeguards/_qois/expr/array.py
compression_safeguards/safeguards/_qois/expr/classification.py
compression_safeguards/safeguards/_qois/expr/combinators.py
compression_safeguards/safeguards/_qois/expr/comparison.py
compression_safeguards/safeguards/_qois/expr/constfold.py
compression_safeguards/safeguards/_qois/expr/data.py
compression_safeguards/safeguards/_qois/expr/divmul.py
compression_safeguards/safeguards/_qois/expr/finite_difference.py
compression_safeguards/safeguards/_qois/expr/group.py
compression_safeguards/safeguards/_qois/expr/hashing.py
compression_safeguards/safeguards/_qois/expr/hyperbolic.py
compression_safeguards/safeguards/_qois/expr/literal.py
compression_safeguards/safeguards/_qois/expr/logexp.py
compression_safeguards/safeguards/_qois/expr/neg.py
compression_safeguards/safeguards/_qois/expr/power.py
compression_safeguards/safeguards/_qois/expr/reciprocal.py
compression_safeguards/safeguards/_qois/expr/reporter.py
compression_safeguards/safeguards/_qois/expr/round.py
compression_safeguards/safeguards/_qois/expr/sign.py
compression_safeguards/safeguards/_qois/expr/square.py
compression_safeguards-1.0.0b1.dist-info/METADATA
compression_safeguards-1.0.0b1.dist-info/WHEEL
compression_safeguards-1.0.0b1.dist-info/licenses/LICENSE
compression_safeguards-1.0.0b1.dist-info/RECORD
