Metadata-Version: 2.4
Name: compression-safeguards
Version: 1.0.0b1
Summary: Fearless lossy compression using safeguards
Author-email: Juniper Tyree <juniper.tyree@helsinki.fi>
Maintainer-email: Juniper Tyree <juniper.tyree@helsinki.fi>
License-Expression: MPL-2.0
License-File: LICENSE
Keywords: compression,fearless,lossy-compression,safe,safeguards
Classifier: Development Status :: 4 - Beta
Classifier: Intended Audience :: Developers
Classifier: Intended Audience :: Science/Research
Classifier: License :: OSI Approved :: Mozilla Public License 2.0 (MPL 2.0)
Classifier: Natural Language :: English
Classifier: Operating System :: OS Independent
Classifier: Programming Language :: Python :: 3
Classifier: Programming Language :: Python :: 3.11
Classifier: Programming Language :: Python :: 3.12
Classifier: Programming Language :: Python :: 3.13
Classifier: Programming Language :: Python :: 3.14
Classifier: Topic :: Scientific/Engineering
Classifier: Topic :: Scientific/Engineering :: Atmospheric Science
Classifier: Topic :: System :: Archiving :: Compression
Classifier: Typing :: Typed
Requires-Python: >=3.11
Requires-Dist: numpy-quaddtype~=1.0
Requires-Dist: numpy~=2.4
Requires-Dist: semver~=3.0
Requires-Dist: sly~=0.5.0
Requires-Dist: typing-extensions~=4.12
